setup.cfg
setup.py
sym_dict/__init__.py
sym_dict/sym_dict.py
sym_dict.egg-info/PKG-INFO
sym_dict.egg-info/SOURCES.txt
sym_dict.egg-info/dependency_links.txt
sym_dict.egg-info/top_level.txt