Metadata-Version: 1.1
Name: sym-dict
Version: 0.2
Summary: Dictionary based tool using symbolic relation to deduce values
Home-page: http://github.com/celliern/sym_dict
Author: Nicolas CELLIER
Author-email: contact@nicolas-cellier.net
License: MIT
Platform: UNKNOWN
Classifier: Programming Language :: Python
Classifier: Development Status :: 3 - Alpha
Classifier: License :: OSI Approved :: MIT License
